bugmark/__init__.py
bugmark/bugmark.py
bugmark/cli.py
bugmark/constants.py
bugmark/core.py
bugmark/models.py
bugmark/storage.py
bugmark/utils.py
bugmark-1.0.0.dist-info/licenses/LICENSE
bugmark-1.0.0.dist-info/METADATA
bugmark-1.0.0.dist-info/WHEEL
bugmark-1.0.0.dist-info/entry_points.txt
bugmark-1.0.0.dist-info/top_level.txt
bugmark-1.0.0.dist-info/RECORD
