Metadata-Version: 2.4
Name: bugmark
Version: 1.0.0
Summary: A command-line bug marker utility for programmers.
Home-page: https://github.com/aaravmaloo/bugmark
Author: Aarav Maloo
Author-email: aaravmaloo06@email.com
Classifier: Programming Language :: Python :: 3
Classifier: License :: OSI Approved :: MIT License
Classifier: Operating System :: OS Independent
Requires-Python: >=3.9
License-File: LICENSE
Dynamic: author
Dynamic: author-email
Dynamic: classifier
Dynamic: description
Dynamic: description-content-type
Dynamic: home-page
Dynamic: license-file
Dynamic: requires-python
Dynamic: summary
